ssmtoenv/__init__.py
ssmtoenv/main.py
ssmtoenv-0.1.4.1.dist-info/METADATA
ssmtoenv-0.1.4.1.dist-info/WHEEL
ssmtoenv-0.1.4.1.dist-info/entry_points.txt
ssmtoenv-0.1.4.1.dist-info/RECORD
